ioutliers/__init__.py
ioutliers/iris.py
ioutliers/outliers.py
ioutliers/teste.py
ioutliersPRO-0.0.1.dist-info/METADATA
ioutliersPRO-0.0.1.dist-info/WHEEL
ioutliersPRO-0.0.1.dist-info/top_level.txt
ioutliersPRO-0.0.1.dist-info/RECORD
