Metadata-Version: 2.1
Name: ioutliersPRO
Version: 0.0.1
Summary: remove potential outliers or Package to easily detect
Home-page: https://.....
Author: Dheiver Santos
Author-email: dheiver.santos@gmail.com
License: UNKNOWN
Platform: UNKNOWN
Classifier: Programming Language :: Python :: 3
Classifier: License :: OSI Approved :: MIT License
Classifier: Operating System :: OS Independent
Requires-Python: >=3.6
Requires-Dist: pandas
Requires-Dist: rrcf
Requires-Dist: sklearn
Requires-Dist: idfops
